polyquack/__init__.py
polyquack/pluralization.py
polyquack/pluralization_ranges.py
polyquack/rules.py
polyquack/translation.py
polyquack-0.2.4.dist-info/LICENSE
polyquack-0.2.4.dist-info/WHEEL
polyquack-0.2.4.dist-info/METADATA
polyquack-0.2.4.dist-info/RECORD
