Metadata-Version: 2.1
Name: polyquack
Version: 0.2.4
Summary: utilities for polyglots
Home-page: https://patryk-media.gitlab.io/polyquack/
License: BSD-3-Clause
Keywords: polyglot,i18n,pluralization
Author: Patryk Bratkowski
Author-email: git@patryk.tech
Requires-Python: >=3.6,<4.0
Classifier: Development Status :: 3 - Alpha
Classifier: Intended Audience :: Developers
Classifier: License :: OSI Approved :: BSD License
Classifier: Operating System :: OS Independent
Classifier: Programming Language :: Python :: 3
Classifier: Programming Language :: Python :: 3.6
Classifier: Programming Language :: Python :: 3.7
Classifier: Programming Language :: Python :: 3.8
Classifier: Topic :: Communications
Classifier: Topic :: Software Development :: Internationalization
Classifier: Topic :: Software Development :: Libraries :: Python Modules
Classifier: Topic :: Text Processing :: Linguistic
Project-URL: Documentation, https://patryk-media.gitlab.io/polyquack/docs/
Project-URL: Repository, https://gitlab.com/patryk-media/polyquack
